latp/__init__.py
latp/base_request.py
latp/cli.py
latp/config.yaml
latp/decorators.py
latp/exceptions.py
latp/http_request.py
latp/models.py
latp/request_manager.py
latp/runner.py
latp/utils.py
latp/websocket_request.py
latp/case_generator/__init__.py
latp/case_generator/core.py
latp/case_generator/template.py
latp/case_generator/utils.py
latp/case_generator/parsers/__init__.py
latp/case_generator/parsers/base_parser.py
latp/case_generator/parsers/har_parser.py
latp/case_generator/parsers/postman_parser.py
latp/case_generator/parsers/swagger_parser.py
latp/case_generator/templates/__init__.py
latp/case_generator/templates/pytest_template.py
latp/case_generator/templates/robot_template.py
latp/case_generator/templates/unittest_template.py
latp/request/__init__.py
latp/request/base_request.py
latp/request/http_request.py
latp/request/request_manager.py
latp/request/websocket_request.py
test_case/__init__.py
test_case/test_latp1.py
test_case/test_latp2.py
latp-0.0.7.dist-info/METADATA
latp-0.0.7.dist-info/WHEEL
latp-0.0.7.dist-info/entry_points.txt
latp-0.0.7.dist-info/top_level.txt
latp-0.0.7.dist-info/RECORD
